confdoggo/__init__.py
confdoggo/__version__.py
confdoggo/clients/__init__.py
confdoggo/clients/fs.py
confdoggo/core.py
confdoggo/frontends/__init__.py
confdoggo/frontends/json.py
confdoggo/frontends/yaml.py
confdoggo/utils.py
confdoggo/watchers/__init__.py
confdoggo/watchers/fs.py
confdoggo-0.1.0a1.dist-info/LICENSE
confdoggo-0.1.0a1.dist-info/WHEEL
confdoggo-0.1.0a1.dist-info/METADATA
confdoggo-0.1.0a1.dist-info/RECORD
