Metadata-Version: 2.1
Name: confdoggo
Version: 0.1.0a1
Summary: Your personal configuration doggo.
Author: Daniele Parmeggiani
Author-email: git@danieleparmeggiani.me
Requires-Python: >=3.6,<4.0
Classifier: Programming Language :: Python :: 3
Classifier: Programming Language :: Python :: 3.6
Classifier: Programming Language :: Python :: 3.7
Classifier: Programming Language :: Python :: 3.8
Classifier: Programming Language :: Python :: 3.9
Provides-Extra: fs-watcher
Provides-Extra: yaml
Requires-Dist: PyYAML (>=5.3.1,<6.0.0); extra == "yaml"
Requires-Dist: pydantic (>=1.6.1)
Requires-Dist: watchdog (>=0.10.3,<0.11.0); extra == "fs-watcher"
